qplex.cpython-313-darwin.so
qplex-1.0.dist-info/RECORD
qplex-1.0.dist-info/WHEEL
qplex-1.0.dist-info/top_level.txt
qplex-1.0.dist-info/METADATA
