Metadata-Version: 2.2
Name: qplex
Version: 1.0
Summary: Performs calculations for models supported by the QPLEX stochastic modeling methodology
License: MIT
Project-URL: Homepage, https://qplex.org/
Project-URL: Documentation, https://qplex.org/documentation/
Project-URL: GitHub, https://github.com/qplex/qplex-python-package/
Dynamic: description
Dynamic: description-content-type
Dynamic: license
Dynamic: project-url
Dynamic: summary
